LICENCE
README.md
setup.py
kseg_py/Kseg.py
kseg_py/__init__.py
kseg_py.egg-info/PKG-INFO
kseg_py.egg-info/SOURCES.txt
kseg_py.egg-info/dependency_links.txt
kseg_py.egg-info/requires.txt
kseg_py.egg-info/top_level.txt