Metadata-Version: 2.1
Name: kseg-py
Version: 0.1.0
Summary: K-segments for Principal Curves Extraction in Python
Home-page: https://github.com/fmborges2/PC_Classifier/
Author: Fernando Elias de Melo Borges
Author-email: fernandoelias.mb@gmail.com
License: MIT License
Keywords: principal curves,k segments
License-File: LICENCE
Requires-Dist: numpy
Requires-Dist: matplotlib
